custodian/__init__.py
custodian/custodian.py
custodian/py.typed
custodian/utils.py
custodian/ansible/__init__.py
custodian/ansible/actions.py
custodian/ansible/interpreter.py
custodian/cli/__init__.py
custodian/cli/converge_geometry.py
custodian/cli/converge_kpoints.py
custodian/cli/cstdn.py
custodian/cli/run_nwchem.py
custodian/cli/run_vasp.py
custodian/cp2k/__init__.py
custodian/cp2k/handlers.py
custodian/cp2k/interpreter.py
custodian/cp2k/jobs.py
custodian/cp2k/utils.py
custodian/cp2k/validators.py
custodian/feff/__init__.py
custodian/feff/handlers.py
custodian/feff/interpreter.py
custodian/feff/jobs.py
custodian/gaussian/__init__.py
custodian/gaussian/handlers.py
custodian/gaussian/jobs.py
custodian/jdftx/__init__.py
custodian/jdftx/jobs.py
custodian/lobster/__init__.py
custodian/lobster/handlers.py
custodian/lobster/jobs.py
custodian/nwchem/__init__.py
custodian/nwchem/handlers.py
custodian/nwchem/jobs.py
custodian/qchem/__init__.py
custodian/qchem/handlers.py
custodian/qchem/jobs.py
custodian/qchem/utils.py
custodian/vasp/__init__.py
custodian/vasp/handlers.py
custodian/vasp/interpreter.py
custodian/vasp/io.py
custodian/vasp/jobs.py
custodian/vasp/utils.py
custodian/vasp/validators.py
custodian-2025.12.14.dist-info/licenses/LICENSE
custodian-2025.12.14.dist-info/METADATA
custodian-2025.12.14.dist-info/WHEEL
custodian-2025.12.14.dist-info/entry_points.txt
custodian-2025.12.14.dist-info/top_level.txt
custodian-2025.12.14.dist-info/RECORD
