Metadata-Version: 2.4
Name: custodian
Version: 2025.12.14
Summary: A simple JIT job management framework in Python.
Author: Matthew Horton, Samuel M. Blau, Stephen Dacek, William Davidson Richards, Xiaohui Qu
Author-email: Janosh Riebesell <janosh.riebesell@gmail.com>, Shyue Ping Ong <ongsp@ucsd.edu>, Andrew Rosen <asrosen@princeton.edu>
Maintainer: Shyue Ping Ong
License: MIT
Project-URL: Docs, https://materialsproject.github.io/custodian
Project-URL: Repo, https://github.com/materialsproject/custodian
Project-URL: Package, https://pypi.org/project/custodian
Keywords: jit,job,just-in-time,management,nwchem,qchem,vasp
Classifier: Development Status :: 5 - Production/Stable
Classifier: Intended Audience :: Science/Research
Classifier: License :: OSI Approved :: MIT License
Classifier: Operating System :: OS Independent
Classifier: Programming Language :: Python :: 3 :: Only
Classifier: Programming Language :: Python :: 3
Classifier: Programming Language :: Python :: 3.10
Classifier: Programming Language :: Python :: 3.11
Classifier: Programming Language :: Python :: 3.12
Classifier: Programming Language :: Python :: 3.13
Classifier: Topic :: Scientific/Engineering :: Chemistry
Classifier: Topic :: Scientific/Engineering :: Physics
Classifier: Topic :: Software Development :: Libraries :: Python Modules
Requires-Python: >=3.10
License-File: LICENSE
Requires-Dist: monty>=2.0.6
Requires-Dist: psutil
Requires-Dist: ruamel.yaml>=0.15.6
Provides-Extra: matsci
Requires-Dist: pymatgen; extra == "matsci"
Provides-Extra: gaussian
Requires-Dist: matplotlib; extra == "gaussian"
Requires-Dist: pymatgen; extra == "gaussian"
Provides-Extra: error-statistics
Requires-Dist: sentry-sdk>=0.8.0; extra == "error-statistics"
Dynamic: license-file
